{
    "key": "group_6a44d34039c52",
    "title": "Page Sections",
    "fields": [
        {
            "key": "field_6a44d3408086d",
            "label": "Sections",
            "name": "sections",
            "aria-label": "",
            "type": "flexible_content",
            "instructions": "",
            "required": 0,
            "conditional_logic": 0,
            "wrapper": {
                "width": "",
                "class": "",
                "id": ""
            },
            "layouts": {
                "layout_6a44d34340089": {
                    "key": "layout_6a44d34340089",
                    "name": "book_slider",
                    "label": "Book slider",
                    "display": "block",
                    "sub_fields": [
                        {
                            "key": "field_6a44d4b580871",
                            "label": "Product slides",
                            "name": "product_slides",
                            "aria-label": "",
                            "type": "repeater",
                            "instructions": "",
                            "required": 0,
                            "conditional_logic": 0,
                            "wrapper": {
                                "width": "",
                                "class": "",
                                "id": ""
                            },
                            "layout": "table",
                            "min": 0,
                            "max": 0,
                            "collapsed": "",
                            "button_label": "Add a new slide",
                            "rows_per_page": 20,
                            "sub_fields": [
                                {
                                    "key": "field_6a44d4f580872",
                                    "label": "Banner setup",
                                    "name": "banner_setup",
                                    "aria-label": "",
                                    "type": "group",
                                    "instructions": "",
                                    "required": 0,
                                    "conditional_logic": 0,
                                    "wrapper": {
                                        "width": "",
                                        "class": "",
                                        "id": ""
                                    },
                                    "layout": "block",
                                    "sub_fields": [
                                        {
                                            "key": "field_6a44d7c080874",
                                            "label": "Image",
                                            "name": "image",
                                            "aria-label": "",
                                            "type": "image",
                                            "instructions": "",
                                            "required": 0,
                                            "conditional_logic": 0,
                                            "wrapper": {
                                                "width": "",
                                                "class": "",
                                                "id": ""
                                            },
                                            "return_format": "id",
                                            "library": "all",
                                            "min_width": "",
                                            "min_height": "",
                                            "min_size": "",
                                            "max_width": "",
                                            "max_height": "",
                                            "max_size": "",
                                            "mime_types": "",
                                            "allow_in_bindings": 0,
                                            "preview_size": "medium"
                                        },
                                        {
                                            "key": "field_6a44d7ca80875",
                                            "label": "Image wrapper class",
                                            "name": "image_wrapper_class",
                                            "aria-label": "",
                                            "type": "text",
                                            "instructions": "",
                                            "required": 0,
                                            "conditional_logic": 0,
                                            "wrapper": {
                                                "width": "",
                                                "class": "",
                                                "id": ""
                                            },
                                            "default_value": "",
                                            "maxlength": "",
                                            "allow_in_bindings": 0,
                                            "placeholder": "",
                                            "prepend": "",
                                            "append": ""
                                        },
                                        {
                                            "key": "field_6a44d7d780876",
                                            "label": "Image class",
                                            "name": "image_class",
                                            "aria-label": "",
                                            "type": "text",
                                            "instructions": "",
                                            "required": 0,
                                            "conditional_logic": 0,
                                            "wrapper": {
                                                "width": "",
                                                "class": "",
                                                "id": ""
                                            },
                                            "default_value": "",
                                            "maxlength": "",
                                            "allow_in_bindings": 0,
                                            "placeholder": "",
                                            "prepend": "",
                                            "append": ""
                                        }
                                    ],
                                    "parent_repeater": "field_6a44d4b580871"
                                },
                                {
                                    "key": "field_6a44d75580873",
                                    "label": "Linked Product",
                                    "name": "linked_product",
                                    "aria-label": "",
                                    "type": "post_object",
                                    "instructions": "",
                                    "required": 0,
                                    "conditional_logic": 0,
                                    "wrapper": {
                                        "width": "",
                                        "class": "",
                                        "id": ""
                                    },
                                    "post_type": [
                                        "product"
                                    ],
                                    "post_status": [
                                        "publish"
                                    ],
                                    "taxonomy": "",
                                    "return_format": "id",
                                    "multiple": 0,
                                    "allow_null": 0,
                                    "allow_in_bindings": 0,
                                    "bidirectional": 0,
                                    "ui": 1,
                                    "bidirectional_target": [],
                                    "parent_repeater": "field_6a44d4b580871"
                                }
                            ]
                        }
                    ],
                    "min": "",
                    "max": ""
                },
                "layout_6a44ea5d78c34": {
                    "key": "layout_6a44ea5d78c34",
                    "name": "author_intro",
                    "label": "Author Introduction",
                    "display": "block",
                    "sub_fields": [],
                    "min": "",
                    "max": ""
                },
                "layout_6a44ea6b78c3a": {
                    "key": "layout_6a44ea6b78c3a",
                    "name": "featured_product",
                    "label": "Featured product",
                    "display": "block",
                    "sub_fields": [
                        {
                            "key": "field_6a44ebb3a8bbf",
                            "label": "Display product",
                            "name": "display_product",
                            "aria-label": "",
                            "type": "post_object",
                            "instructions": "",
                            "required": 0,
                            "conditional_logic": 0,
                            "wrapper": {
                                "width": "",
                                "class": "",
                                "id": ""
                            },
                            "post_type": [
                                "product"
                            ],
                            "post_status": [
                                "publish"
                            ],
                            "taxonomy": "",
                            "return_format": "id",
                            "multiple": 0,
                            "allow_null": 0,
                            "allow_in_bindings": 0,
                            "bidirectional": 0,
                            "ui": 1,
                            "bidirectional_target": []
                        }
                    ],
                    "min": "",
                    "max": ""
                },
                "layout_6a44ea8c71bc6": {
                    "key": "layout_6a44ea8c71bc6",
                    "name": "list_of_products",
                    "label": "List of products",
                    "display": "block",
                    "sub_fields": [],
                    "min": "",
                    "max": ""
                }
            },
            "min": "",
            "max": "",
            "button_label": "Add new section"
        }
    ],
    "location": [
        [
            {
                "param": "post_type",
                "operator": "==",
                "value": "page"
            }
        ]
    ],
    "menu_order": 0,
    "position": "normal",
    "style": "default",
    "label_placement": "top",
    "instruction_placement": "label",
    "hide_on_screen": [
        "the_content",
        "excerpt",
        "discussion",
        "comments",
        "revisions",
        "author",
        "format",
        "send-trackbacks"
    ],
    "active": true,
    "description": "",
    "show_in_rest": 0,
    "display_title": "",
    "modified": 1782901710
}
